{
  "request": {
    "name": "updatedResidentialDevice",
    "description": "demo description",
    "directConnectivity": "yes",
    "ip": "1.2.3.4",
    "port": 1024,
    "password": "+rA778Li2dL",
    "allow": "alaw",
    "fromDomain": null,
    "ddiIn": "yes",
    "maxCalls": 1,
    "t38Passthrough": "no",
    "transformationRuleSet": null,
    "outgoingDdi": null,
    "language": null,
    "proxyUser": 2,
    "transport": "udp"
  },
  "response": {
    "body": {
      "name": "updatedResidentialDevice",
      "description": "demo description",
      "transport": "udp",
      "ip": "1.2.3.4",
      "port": 1024,
      "password": "+rA778Li2dL",
      "allow": "alaw",
      "fromDomain": null,
      "directConnectivity": "yes",
      "ddiIn": "yes",
      "maxCalls": 1,
      "t38Passthrough": "no",
      "rtpEncryption": false,
      "multiContact": true,
      "ruriDomain": null,
      "id": 1,
      "company": 4,
      "transformationRuleSet": null,
      "outgoingDdi": null,
      "language": null,
      "proxyUser": 2
    },
    "headers": {
      "content-type": "application/json; charset=utf-8"
    },
    "statusCode": 200
  }
}